Metadata-Version: 1.1
Name: cheapnamedtuple
Version: 1.1.2
Summary: Faster reimplementation of stdlib collections.namedtuple
Home-page: https://github.com/arnauorriols/cheapnamedtuple
Author: Arnau Orriols
Author-email: dev@arnauorriols.com
License: MIT License
Keywords: namedtuple exec performance
Platform: UNKNOWN
Classifier: Intended Audience :: Developers
Classifier: Programming Language :: Python :: 2 :: Only
